setup.py
splicer_console.py
splicer_console.egg-info/PKG-INFO
splicer_console.egg-info/SOURCES.txt
splicer_console.egg-info/dependency_links.txt
splicer_console.egg-info/requires.txt
splicer_console.egg-info/top_level.txt