Metadata-Version: 1.0
Name: splicer-console
Version: 0.0.2
Summary: Console support for Splicer Apps
Home-page: http://github.com/trivio/splicer_console
Author: Scott Robertson
Author-email: scott@triv.io
License: UNKNOWN
Platform: UNKNOWN
Classifier: Programming Language :: Python
Classifier: License :: OSI Approved :: MIT License
Classifier: Operating System :: OS Independent
Classifier: Development Status :: 3 - Alpha
Classifier: Intended Audience :: Developers
Classifier: Topic :: Software Development
